clients/__init__.py
clients/beatleader/__init__.py
clients/beatleader/client.py
clients/beatleader/errors.py
clients/beatleader/py.typed
clients/beatleader/types.py
clients/beatleader/api/__init__.py
clients/beatleader/api/beast_saber/__init__.py
clients/beatleader/api/beast_saber/beast_saber_get_all.py
clients/beatleader/api/beast_saber/beast_saber_nominate.py
clients/beatleader/api/clan/__init__.py
clients/beatleader/api/clan/clan_get_all.py
clients/beatleader/api/clan/clan_get_clan.py
clients/beatleader/api/clan/clan_get_clan_by_id.py
clients/beatleader/api/clan/clan_get_clan_with_maps.py
clients/beatleader/api/clan/clan_get_clan_with_maps_by_id.py
clients/beatleader/api/clan/clan_get_history.py
clients/beatleader/api/clan/clan_global_map.py
clients/beatleader/api/leaderboard/__init__.py
clients/beatleader/api/leaderboard/leaderboard_get.py
clients/beatleader/api/leaderboard/leaderboard_get_all.py
clients/beatleader/api/leaderboard/leaderboard_get_clan_rankings.py
clients/beatleader/api/leaderboard/leaderboard_get_scoregraph.py
clients/beatleader/api/modifiers/__init__.py
clients/beatleader/api/modifiers/modifiers_get_modifiers.py
clients/beatleader/api/patreon/__init__.py
clients/beatleader/api/patreon/patreon_refresh_my_patreon.py
clients/beatleader/api/player/__init__.py
clients/beatleader/api/player/player_get.py
clients/beatleader/api/player/player_get_beat_saver.py
clients/beatleader/api/player/player_get_discord.py
clients/beatleader/api/player/player_get_followers.py
clients/beatleader/api/player/player_get_followers_info.py
clients/beatleader/api/player/player_get_founded_clan.py
clients/beatleader/api/player/player_get_participating_events.py
clients/beatleader/api/player/player_get_patreon.py
clients/beatleader/api/player/player_get_players.py
clients/beatleader/api/player/player_get_ranked_maps.py
clients/beatleader/api/player_scores/__init__.py
clients/beatleader/api/player_scores/player_scores_acc_graph.py
pleb_saberlist-0.2.0.dist-info/LICENSE
pleb_saberlist-0.2.0.dist-info/METADATA
pleb_saberlist-0.2.0.dist-info/WHEEL
pleb_saberlist-0.2.0.dist-info/entry_points.txt
pleb_saberlist-0.2.0.dist-info/top_level.txt
pleb_saberlist-0.2.0.dist-info/RECORD
