Metadata-Version: 2.1
Name: pleb-saberlist
Version: 0.2.0
Summary: Beat Saber playlist tool
Author-email: blee <git@blee.tube>
License: Apache License
Project-URL: Homepage, https://git.satstack.dev/blee/beatsaber-playlist-tool
Keywords: reddit
Classifier: Programming Language :: Python
Classifier: Programming Language :: Python :: 3
Classifier: Programming Language :: Python :: 3.11
Classifier: Programming Language :: Python :: 3.12
Classifier: Programming Language :: Python :: Implementation :: CPython
Classifier: Programming Language :: Python :: Implementation :: PyPy
Classifier: Topic :: Utilities
Classifier: License :: OSI Approved :: Apache Software License
Requires-Python: >=3.8.10
License-File: LICENSE
Requires-Dist: build >=1.2.1
Requires-Dist: requests >=2.31.0
Requires-Dist: pytest >=8.1.1
Requires-Dist: python-dotenv >=1.0.1
Requires-Dist: PyScoreSaber >=1.0.10
Requires-Dist: beatsaver >=1.0.1
